odoo/addons/product_attribute_set_completeness/README.rst
odoo/addons/product_attribute_set_completeness/__init__.py
odoo/addons/product_attribute_set_completeness/__manifest__.py
odoo/addons/product_attribute_set_completeness/components/__init__.py
odoo/addons/product_attribute_set_completeness/components/product_template_event_listener.py
odoo/addons/product_attribute_set_completeness/i18n/product_attribute_set_completeness.pot
odoo/addons/product_attribute_set_completeness/readme/CONTRIBUTORS.rst
odoo/addons/product_attribute_set_completeness/readme/DESCRIPTION.rst
odoo/addons/product_attribute_set_completeness/readme/USAGE.rst
odoo/addons/product_attribute_set_completeness/static/description/icon.png
odoo/addons/product_attribute_set_completeness/static/description/index.html
odoo/addons/product_attribute_set_completeness/views/product_template_view.xml
odoo14_addon_product_attribute_set_completeness-14.0.2.0.0.dist-info/METADATA
odoo14_addon_product_attribute_set_completeness-14.0.2.0.0.dist-info/WHEEL
odoo14_addon_product_attribute_set_completeness-14.0.2.0.0.dist-info/top_level.txt
odoo14_addon_product_attribute_set_completeness-14.0.2.0.0.dist-info/RECORD
