Metadata-Version: 2.1
Name: odoo14-addon-product-attribute-set-completeness
Version: 14.0.2.0.0
Summary: Product Attribute Set Completeness
Home-page: https://github.com/OCA/odoo-pim
Author: ACSONE SA/NV, Odoo Community Association (OCA)
Author-email: support@odoo-community.org
License: AGPL-3
Platform: UNKNOWN
Classifier: Programming Language :: Python
Classifier: Framework :: Odoo
Classifier: Framework :: Odoo :: 14.0
Classifier: License :: OSI Approved :: GNU Affero General Public License v3
Requires-Python: >=3.6
Requires-Dist: odoo14-addon-attribute-set-completeness
Requires-Dist: odoo14-addon-product-attribute-set
Requires-Dist: odoo (<14.1dev,>=14.0a)
